{
    "history": [
        {
            "source": "/Users/Stephen/Sites/hpadesign.com/projects",
            "docker_user": "stephenneal",
            "docker_repo": "projects.hpadesign.com",
            "docker_repo_tag": "latest",
            "actions": {
                "build": true,
                "push": false,
                "run": false
            },
            "time": "2019-03-20 10:29",
            "tasks": []
        },
        {
            "source": "/Users/Stephen/Sites/hpadesign.com/projects",
            "docker_user": "stephenneal",
            "docker_repo": "projects.hpadesign.com",
            "docker_repo_tag": "latest",
            "host_port": "8181",
            "container_port": "8181",
            "actions": {
                "build": true,
                "push": false,
                "run": true
            },
            "time": "2019-03-20 11:09",
            "tasks": [
                "0: Built Docker image stephenneal/projects.hpadesign.com:latest",
                "1: Running Docker image stephenneal/projects.hpadesign.com:latest or local machine"
            ]
        },
        {
            "source": "/Users/Stephen/Sites/hpadesign.com/projects",
            "docker_user": "stephenneal",
            "docker_repo": "projects.hpadesign.com",
            "docker_repo_tag": "latest",
            "host_port": "8181",
            "container_port": "8181",
            "actions": {
                "build": true,
                "push": false,
                "run": false
            },
            "time": "2019-03-20 11:15",
            "tasks": [
                "0: Built Docker image stephenneal/projects.hpadesign.com:latest"
            ]
        }
    ]
}